samtoolsbox/__init__.py
samtoolsbox-0.1.dist-info/METADATA
samtoolsbox-0.1.dist-info/WHEEL
samtoolsbox-0.1.dist-info/top_level.txt
samtoolsbox-0.1.dist-info/RECORD
