Metadata-Version: 2.1
Name: samtoolsbox
Version: 0.1
Summary: sam's tools box
Home-page: http://b.isam.top/
Author: sam
Author-email: 1102566608@qq.com
License: BSD License
Platform: all
